setup.py
iclstat_distributions/Binomialdistribution.py
iclstat_distributions/Gaussiandistribution.py
iclstat_distributions/Generaldistribution.py
iclstat_distributions/__init__.py
iclstat_distributions.egg-info/PKG-INFO
iclstat_distributions.egg-info/SOURCES.txt
iclstat_distributions.egg-info/dependency_links.txt
iclstat_distributions.egg-info/not-zip-safe
iclstat_distributions.egg-info/top_level.txt