Metadata-Version: 1.0
Name: iclstat-distributions
Version: 1.0
Summary: Binomial and Gaussian distributions
Home-page: UNKNOWN
Author: Iker Chasco Llorente
Author-email: i_chasco@hotmail.com
License: UNKNOWN
Platform: UNKNOWN
